chemschema/__init__.py
chemschema/base.py
chemschema/bingo/__init__.py
chemschema/bingo/comparators.py
chemschema/bingo/functions.py
chemschema/bingo/index.py
chemschema/bingo/types.py
chemschema/py.typed
chemschema/rdkit/__init__.py
chemschema/rdkit/types.py
chemschema/utils.py
chemschema-0.0.1.dist-info/WHEEL
chemschema-0.0.1.dist-info/METADATA
chemschema-0.0.1.dist-info/RECORD
